LICENSE
README.md
setup.py
automation_fw_helper/__init__.py
automation_fw_helper.egg-info/PKG-INFO
automation_fw_helper.egg-info/SOURCES.txt
automation_fw_helper.egg-info/dependency_links.txt
automation_fw_helper.egg-info/requires.txt
automation_fw_helper.egg-info/top_level.txt
automation_fw_helper/common/__init__.py
automation_fw_helper/common/dir.py
automation_fw_helper/common/log.py
automation_fw_helper/infrastructure/__init__.py
automation_fw_helper/infrastructure/frame_api.py
automation_fw_helper/infrastructure/platform.py
automation_fw_helper/proxy/__init__.py
automation_fw_helper/proxy/airtest_proxy.py
automation_fw_helper/proxy/uiautomation_proxy.py